ludo/__init__.py
ludo-0.0.1.dist-info/METADATA
ludo-0.0.1.dist-info/WHEEL
ludo-0.0.1.dist-info/top_level.txt
ludo-0.0.1.dist-info/RECORD
