Metadata-Version: 2.4
Name: ludo
Version: 0.0.1
Summary: Dummy lock package for ludo
Author: AutoPublisher
